main/__init__.py
main/main.py
httpsiam-3.dist-info/LICENSE
httpsiam-3.dist-info/METADATA
httpsiam-3.dist-info/WHEEL
httpsiam-3.dist-info/entry_points.txt
httpsiam-3.dist-info/top_level.txt
httpsiam-3.dist-info/RECORD
